rocketchip_pkg/__init__.py
rocketchip_pkg/rocketchip.py
rocketchip_pkg/rules/align_reads/STAR_paired.txt
rocketchip_pkg/rules/align_reads/STAR_single.txt
rocketchip_pkg/rules/align_reads/bowtie2_paired.txt
rocketchip_pkg/rules/align_reads/bowtie2_single.txt
rocketchip_pkg/rules/align_reads/bwa_mem_paired.txt
rocketchip_pkg/rules/align_reads/bwa_mem_single.txt
rocketchip_pkg/rules/bam_to_bigwig/bam_to_bigwig.txt
rocketchip_pkg/rules/call_peaks/cisgenome/cisgenome_no_control.txt
rocketchip_pkg/rules/call_peaks/cisgenome/cisgenome_with_control.txt
rocketchip_pkg/rules/call_peaks/genrich/genrich_no_control.txt
rocketchip_pkg/rules/call_peaks/genrich/genrich_with_control.txt
rocketchip_pkg/rules/call_peaks/macs3/macs3_no_control.txt
rocketchip_pkg/rules/call_peaks/macs3/macs3_with_control.txt
rocketchip_pkg/rules/call_peaks/peakseq/peakseq_with_control.txt
rocketchip_pkg/rules/call_peaks/pepr/pepr_with_control.txt
rocketchip_pkg/rules/evaluate_peaks/evals.txt
rocketchip_pkg/rules/fastqc/postprocessing_paired.txt
rocketchip_pkg/rules/fastqc/postprocessing_single.txt
rocketchip_pkg/rules/fastqc/preprocessing_paired.txt
rocketchip_pkg/rules/fastqc/preprocessing_single.txt
rocketchip_pkg/rules/get_genome/local_genome.txt
rocketchip_pkg/rules/get_genome/remote_fa_gz_genome.txt
rocketchip_pkg/rules/get_genome/remote_hg38_genome.txt
rocketchip_pkg/rules/get_genome/remote_tar_gz_genome.txt
rocketchip_pkg/rules/get_reads/local_reads_paired.txt
rocketchip_pkg/rules/get_reads/local_reads_single.txt
rocketchip_pkg/rules/get_reads/remote_reads_paired.txt
rocketchip_pkg/rules/get_reads/remote_reads_single.txt
rocketchip_pkg/rules/index_genome/STAR.txt
rocketchip_pkg/rules/index_genome/bowtie2.txt
rocketchip_pkg/rules/index_genome/bwa_mem.txt
rocketchip_pkg/rules/make_dir/make_dir.txt
rocketchip_pkg/rules/mark_dup/fake_dedup.txt
rocketchip_pkg/rules/mark_dup/picard_dedup.txt
rocketchip_pkg/rules/mark_dup/sambamba_dedup.txt
rocketchip_pkg/rules/mark_dup/samtools_dedup.txt
rocketchip-2.0.1.dist-info/LICENSE
rocketchip-2.0.1.dist-info/METADATA
rocketchip-2.0.1.dist-info/WHEEL
rocketchip-2.0.1.dist-info/entry_points.txt
rocketchip-2.0.1.dist-info/top_level.txt
rocketchip-2.0.1.dist-info/RECORD
