Metadata-Version: 2.1
Name: rocketchip
Version: 2.0.1
Summary: A pip-installable package for Rocketchip
Home-page: https://github.com/vhaghani26/rocketchip
Author: Viktoria Haghani
Author-email: vhaghani@ucdavis.edu
License: MIT
Classifier: Programming Language :: Python :: 3
Classifier: License :: OSI Approved :: MIT License
Classifier: Operating System :: OS Independent
Requires-Python: >=3.6
License-File: LICENSE
Requires-Dist: pyyaml>=6.0.1
Requires-Dist: snakemake>=7.32.4
Requires-Dist: macs3>=3.0.0b3
